cryocon-22c-controller/__init__.py
cryocon-22c-controller/cryocon_controller.py
cryocon_22c_controller/__init__.py
cryocon_22c_controller/_version.py
cryocon_22c_controller/cryocon_controller.py
cryocon_22c_controller-0.0.3.post2.dist-info/LICENSE
cryocon_22c_controller-0.0.3.post2.dist-info/METADATA
cryocon_22c_controller-0.0.3.post2.dist-info/WHEEL
cryocon_22c_controller-0.0.3.post2.dist-info/top_level.txt
cryocon_22c_controller-0.0.3.post2.dist-info/RECORD
