Metadata-Version: 2.1
Name: cryocon-22c-controller
Version: 0.0.3.post2
Summary: A package for controlling CryoCon 22C Temperature Controllers
Home-page: https://github.com/bicarlsen/cryocon-22c-controller
Author: Brian Carlsen
Author-email: carlsen.bri@gmail.com
License: UNKNOWN
Project-URL: Source Code, https://github.com/bicarlsen/cryocon-22c-controller
Project-URL: Bug Tracker, https://github.com/bicarlsen/cryocon-22c-controller/issues
Keywords: cryocon,cryocon 22c,temperature controller,cryostat,cryo
Platform: UNKNOWN
Classifier: Programming Language :: Python :: 3
Classifier: License :: OSI Approved :: GNU General Public License v3 (GPLv3)
Classifier: Operating System :: OS Independent
Classifier: Development Status :: 3 - Alpha
License-File: LICENSE
Requires-Dist: easy-scpi
Requires-Dist: pyvisa-py
